file_to_qr/__init__.py
file_to_qr/main.py
qr_to_file/__init__.py
qr_to_file/assembler.py
qr_to_file/main.py
qr_to_file/protocol.py
qr_to_file/qr.py
qr_to_file/webcam.py
file2qr-0.0.3.dist-info/METADATA
file2qr-0.0.3.dist-info/WHEEL
file2qr-0.0.3.dist-info/entry_points.txt
file2qr-0.0.3.dist-info/top_level.txt
file2qr-0.0.3.dist-info/RECORD
