Metadata-Version: 2.1
Name: file2qr
Version: 0.0.3
Summary: Tools for sending and receiving a file via QR codes
Home-page: https://github.com/six-two/react-file2qr
Author: six-two
Author-email: pip@six-two.dev
License: MIT License
Classifier: Operating System :: POSIX :: Linux
Classifier: Programming Language :: Python :: 3
Classifier: Programming Language :: Python :: 3.9
Classifier: Programming Language :: Python :: 3.10
Classifier: Programming Language :: Python :: 3.11
Requires-Python: >=3.9
Requires-Dist: Pillow
Requires-Dist: pyzbar
Requires-Dist: python-opencv
